ctkaddons/__init__.py
ctkaddons/calender.py
ctkaddons/date_select.py
ctkaddons/multipane.py
ctkaddons/errors/multipane_errors.py
ctkaddons-0.0.8.dist-info/METADATA
ctkaddons-0.0.8.dist-info/WHEEL
ctkaddons-0.0.8.dist-info/top_level.txt
ctkaddons-0.0.8.dist-info/RECORD
