Metadata-Version: 2.1
Name: ctkaddons
Version: 0.0.8
Summary: A package that add uneccessary widgets to customtkinter
Author-email: TonyLovesMusic <tony.tonylovescoding@example.com>
Project-URL: Homepage, https://github.com/TonyLovesCoding/CTkAddons
Project-URL: Issue, https://github.com/TonyLovesCoding/CTkAddons/issues
Keywords: customtkinter,widgets,addon,calender
Classifier: Development Status :: 1 - Planning
Classifier: Programming Language :: Python
Classifier: Intended Audience :: Developers
Classifier: Operating System :: OS Independent
Requires-Python: >=3.12
Requires-Dist: customtkinter
Requires-Dist: tkscenes>=0.1.2
Requires-Dist: multipledispatch
Requires-Dist: pillow>=11.0.0
